setup.cfg
setup.py
fixedwidthwriter/__init__.py
fixedwidthwriter.egg-info/PKG-INFO
fixedwidthwriter.egg-info/SOURCES.txt
fixedwidthwriter.egg-info/dependency_links.txt
fixedwidthwriter.egg-info/requires.txt
fixedwidthwriter.egg-info/top_level.txt