Metadata-Version: 1.1
Name: fixedwidthwriter
Version: 1.0.1
Summary: A class to write fixed-width files with an interface similar to python`s csv writer
Home-page: https://github.com/ArthurPBressan/py-fixedwidthwriter
Author: Arthur Bressan
Author-email: arthurpbressan@gmail.com
License: UNKNOWN
Download-URL: https://github.com/ArthurPBressan/py-fixedwidthwriter/tarball/1.0.1
Keywords: file writer,fixed width
Platform: UNKNOWN
